blink1/__init__.py
blink1/blink1.py
blink1/flash.py
blink1/kelvin.py
blink1/shine.py
blink1-0.4.0.dist-info/licenses/LICENSE.txt
blink1-0.4.0.dist-info/METADATA
blink1-0.4.0.dist-info/WHEEL
blink1-0.4.0.dist-info/entry_points.txt
blink1-0.4.0.dist-info/top_level.txt
blink1-0.4.0.dist-info/RECORD
