Metadata-Version: 2.4
Name: blink1
Version: 0.4.0
Summary: Official blink(1) control library
Author-email: Salim Fadhley <salimfadhley@gmail.com>, "Tod E. Kurt" <todbotdotcom@gmail.com>
License-Expression: MIT
Project-URL: Homepage, https://github.com/todbot/blink1-python
Classifier: Development Status :: 2 - Pre-Alpha
Classifier: Environment :: Console
Classifier: Intended Audience :: Developers
Classifier: Natural Language :: English
Classifier: Operating System :: OS Independent
Classifier: Programming Language :: Python :: 3
Classifier: Topic :: Software Development :: Testing
License-File: LICENSE.txt
Requires-Dist: click
Requires-Dist: hidapi>=0.13.1
Requires-Dist: webcolors
Dynamic: license-file
